[
	{
		"model": "movies.actor",
		"pk": 40462,
		"fields": {
			"movie_id": 330457,
			"name": "Kristen Bell",
			"character": "Anna (voice)",
			"profile_photo": "https://image.tmdb.org/t/p/original/9DoDVUkoXhT3O2R1RymPlOfUryl.jpg"
		}
	},
	{
		"model": "movies.actor",
		"pk": 19394,
		"fields": {
			"movie_id": 330457,
			"name": "Idina Menzel",
			"character": "Elsa (voice)",
			"profile_photo": "https://image.tmdb.org/t/p/original/s2AjAX3qr0cZpfEdiEyYko9SGrZ.jpg"
		}
	},
	{
		"model": "movies.actor",
		"pk": 221611,
		"fields": {
			"movie_id": 330457,
			"name": "Jonathan Groff",
			"character": "Kristoff (voice)",
			"profile_photo": "https://image.tmdb.org/t/p/original/3kmnYKAzSc3Lp7iK5pcj97Hx9Cm.jpg"
		}
	},
	{
		"model": "movies.actor",
		"pk": 54415,
		"fields": {
			"movie_id": 330457,
			"name": "Josh Gad",
			"character": "Olaf (voice)",
			"profile_photo": "https://image.tmdb.org/t/p/original/oyEprEGF1aqWAqUZNx3yujJ9gPn.jpg"
		}
	},
	{
		"model": "movies.actor",
		"pk": 1225953,
		"fields": {
			"movie_id": 330457,
			"name": "Sterling K. Brown",
			"character": "Lieutenant Mattias (voice)",
			"profile_photo": "https://image.tmdb.org/t/p/original/l0Zth6GbkZbMpyl52RPMCO7GQA5.jpg"
		}
	},
	{
		"model": "movies.actor",
		"pk": 16483,
		"fields": {
			"movie_id": 480042,
			"name": "Sylvester Stallone",
			"character": "Ray Breslin",
			"profile_photo": "https://image.tmdb.org/t/p/original/gnmwOa46C2TP35N7ARSzboTdx2u.jpg"
		}
	},
	{
		"model": "movies.actor",
		"pk": 543530,
		"fields": {
			"movie_id": 480042,
			"name": "Dave Bautista",
			"character": "Trent DeRosa",
			"profile_photo": "https://image.tmdb.org/t/p/original/oZDL1VprkUEFhOtG5WcVjudj5ks.jpg"
		}
	},
	{
		"model": "movies.actor",
		"pk": 5915,
		"fields": {
			"movie_id": 480042,
			"name": "Jaime King",
			"character": "Abigail Ross",
			"profile_photo": "https://image.tmdb.org/t/p/original/zxRIrvJly1KIZdLA8c3B024LezU.jpg"
		}
	},
	{
		"model": "movies.actor",
		"pk": 21354,
		"fields": {
			"movie_id": 480042,
			"name": "Russell Wong",
			"character": "Wu Zhang",
			"profile_photo": "https://image.tmdb.org/t/p/original/ow2nODo1eKRchSLJMjEW7BUTXgy.jpg"
		}
	},
	{
		"model": "movies.actor",
		"pk": 1614437,
		"fields": {
			"movie_id": 480042,
			"name": "Danni Wang",
			"character": "Ling May",
			"profile_photo": "https://image.tmdb.org/t/p/original/rhv7TrEh7oNWq2tOP9Sg7YLh77g.jpg"
		}
	},
	{
		"model": "movies.actor",
		"pk": 1136406,
		"fields": {
			"movie_id": 429617,
			"name": "Tom Holland",
			"character": "Peter Parker / Spider-Man",
			"profile_photo": "https://image.tmdb.org/t/p/original/ip7aXVH8s6wXv8cY6KI14OZgCI8.jpg"
		}
	},
	{
		"model": "movies.actor",
		"pk": 131,
		"fields": {
			"movie_id": 429617,
			"name": "Jake Gyllenhaal",
			"character": "Quentin Beck / Mysterio",
			"profile_photo": "https://image.tmdb.org/t/p/original/92sBuFC8tWPG7IqGDJNxysT7tIF.jpg"
		}
	},
	{
		"model": "movies.actor",
		"pk": 505710,
		"fields": {
			"movie_id": 429617,
			"name": "Zendaya",
			"character": "Michelle \"MJ\" Jones",
			"profile_photo": "https://image.tmdb.org/t/p/original/r3A7ev7QkjOGocVn3kQrJ0eOouk.jpg"
		}
	},
	{
		"model": "movies.actor",
		"pk": 15277,
		"fields": {
			"movie_id": 429617,
			"name": "Jon Favreau",
			"character": "Harold \"Happy\" Hogan",
			"profile_photo": "https://image.tmdb.org/t/p/original/rOVBKURoR7TrG8MYxTuNUFj3E68.jpg"
		}
	},
	{
		"model": "movies.actor",
		"pk": 2231,
		"fields": {
			"movie_id": 429617,
			"name": "Samuel L. Jackson",
			"character": "Nick Fury",
			"profile_photo": "https://image.tmdb.org/t/p/original/qjYcO8jKNlb7lnJ05vh2U7lNt8r.jpg"
		}
	},
	{
		"model": "movies.actor",
		"pk": 73421,
		"fields": {
			"movie_id": 475557,
			"name": "Joaquin Phoenix",
			"character": "Arthur Fleck / Joker",
			"profile_photo": "https://image.tmdb.org/t/p/original/zixTWuMZ1D8EopgOhLVZ6Js2ux3.jpg"
		}
	},
	{
		"model": "movies.actor",
		"pk": 380,
		"fields": {
			"movie_id": 475557,
			"name": "Robert De Niro",
			"character": "Murray Franklin",
			"profile_photo": "https://image.tmdb.org/t/p/original/8Bgdfv1oN9Mw0YuMHP6fw8KzDkc.jpg"
		}
	},
	{
		"model": "movies.actor",
		"pk": 1545693,
		"fields": {
			"movie_id": 475557,
			"name": "Zazie Beetz",
			"character": "Sophie Dumond",
			"profile_photo": "https://image.tmdb.org/t/p/original/sgxzT54GnvgeMnOZgpQQx9csAdd.jpg"
		}
	},
	{
		"model": "movies.actor",
		"pk": 4432,
		"fields": {
			"movie_id": 475557,
			"name": "Frances Conroy",
			"character": "Penny Fleck",
			"profile_photo": "https://image.tmdb.org/t/p/original/aJRQAkO24L6bH8qkkE5Iv1nA3gf.jpg"
		}
	},
	{
		"model": "movies.actor",
		"pk": 16841,
		"fields": {
			"movie_id": 475557,
			"name": "Brett Cullen",
			"character": "Thomas Wayne",
			"profile_photo": "https://image.tmdb.org/t/p/original/o94R8Z59lrwbZ0LcUkDSPu1GS7q.jpg"
		}
	},
	{
		"model": "movies.actor",
		"pk": 119589,
		"fields": {
			"movie_id": 420818,
			"name": "Donald Glover",
			"character": "Simba (voice)",
			"profile_photo": "https://image.tmdb.org/t/p/original/36o5mpbQVdxOf9kUxWw7SllOuk.jpg"
		}
	},
	{
		"model": "movies.actor",
		"pk": 14386,
		"fields": {
			"movie_id": 420818,
			"name": "Beyoncé Knowles",
			"character": "Nala (voice)",
			"profile_photo": "https://image.tmdb.org/t/p/original/9MgDCYBBVBl4lM1DuxNIIbCHlKy.jpg"
		}
	},
	{
		"model": "movies.actor",
		"pk": 15152,
		"fields": {
			"movie_id": 420818,
			"name": "James Earl Jones",
			"character": "Mufasa (voice)",
			"profile_photo": "https://image.tmdb.org/t/p/original/oqMPIsXrl9SZkRfIKN08eFROmH6.jpg"
		}
	},
	{
		"model": "movies.actor",
		"pk": 5294,
		"fields": {
			"movie_id": 420818,
			"name": "Chiwetel Ejiofor",
			"character": "Scar (voice)",
			"profile_photo": "https://image.tmdb.org/t/p/original/kq5DDnqqofoRI0t6ddtRlsJnNPT.jpg"
		}
	},
	{
		"model": "movies.actor",
		"pk": 1981,
		"fields": {
			"movie_id": 420818,
			"name": "Alfre Woodard",
			"character": "Sarabi (voice)",
			"profile_photo": "https://image.tmdb.org/t/p/original/eoBvK34M52no6voo9Qibrd1S0nX.jpg"
		}
	},
	{
		"model": "movies.actor",
		"pk": 6193,
		"fields": {
			"movie_id": 466272,
			"name": "Leonardo DiCaprio",
			"character": "Rick Dalton",
			"profile_photo": "https://image.tmdb.org/t/p/original/aLUFp0zWpLVyIOgY0scIpuuKZLE.jpg"
		}
	},
	{
		"model": "movies.actor",
		"pk": 287,
		"fields": {
			"movie_id": 466272,
			"name": "Brad Pitt",
			"character": "Cliff Booth",
			"profile_photo": "https://image.tmdb.org/t/p/original/kc3M04QQAuZ9woUvH3Ju5T7ZqG5.jpg"
		}
	},
	{
		"model": "movies.actor",
		"pk": 234352,
		"fields": {
			"movie_id": 466272,
			"name": "Margot Robbie",
			"character": "Sharon Tate",
			"profile_photo": "https://image.tmdb.org/t/p/original/ecv9SBN9m1cEZFfSopph6wf8fk.jpg"
		}
	},
	{
		"model": "movies.actor",
		"pk": 46593,
		"fields": {
			"movie_id": 466272,
			"name": "Emile Hirsch",
			"character": "Jay Sebring",
			"profile_photo": "https://image.tmdb.org/t/p/original/NQjX6KjtDDyLnvbxhrU9xQWaYJ.jpg"
		}
	},
	{
		"model": "movies.actor",
		"pk": 1392137,
		"fields": {
			"movie_id": 466272,
			"name": "Margaret Qualley",
			"character": "Pussycat",
			"profile_photo": "https://image.tmdb.org/t/p/original/mcjZQfO8yh4HltiyiSrrRqhOLzz.jpg"
		}
	},
	{
		"model": "movies.actor",
		"pk": 1596934,
		"fields": {
			"movie_id": 290859,
			"name": "Natalia Reyes",
			"character": "Daniela \"Dani\" Ramos",
			"profile_photo": "https://image.tmdb.org/t/p/original/9N7FNKUhjtinrNPy8ANvXrB7iEr.jpg"
		}
	},
	{
		"model": "movies.actor",
		"pk": 1110405,
		"fields": {
			"movie_id": 290859,
			"name": "Mackenzie Davis",
			"character": "Grace",
			"profile_photo": "https://image.tmdb.org/t/p/original/ekQbEIKh26jbz17P0wwLbo6uNs9.jpg"
		}
	},
	{
		"model": "movies.actor",
		"pk": 2713,
		"fields": {
			"movie_id": 290859,
			"name": "Linda Hamilton",
			"character": "Sarah Connor",
			"profile_photo": "https://image.tmdb.org/t/p/original/zRQSWGCmVkYC7s0WxSJla5R4dPX.jpg"
		}
	},
	{
		"model": "movies.actor",
		"pk": 111016,
		"fields": {
			"movie_id": 290859,
			"name": "Gabriel Luna",
			"character": "Rev-9",
			"profile_photo": "https://image.tmdb.org/t/p/original/mYVDObiZuw7DmsBHsLfZIAn37Tw.jpg"
		}
	},
	{
		"model": "movies.actor",
		"pk": 1100,
		"fields": {
			"movie_id": 290859,
			"name": "Arnold Schwarzenegger",
			"character": "Carl / The Terminator",
			"profile_photo": "https://image.tmdb.org/t/p/original/dUAFC9E1oVTDKFXCYcetPuOMXYA.jpg"
		}
	},
	{
		"model": "movies.actor",
		"pk": 2450298,
		"fields": {
			"movie_id": 645541,
			"name": "Grant Martin",
			"character": "Rauge",
			"profile_photo": []
		}
	},
	{
		"model": "movies.actor",
		"pk": 2450299,
		"fields": {
			"movie_id": 645541,
			"name": "Michelle Medoff",
			"character": "Emma",
			"profile_photo": []
		}
	},
	{
		"model": "movies.actor",
		"pk": 2450300,
		"fields": {
			"movie_id": 645541,
			"name": "Jack William",
			"character": "Mac",
			"profile_photo": []
		}
	},
	{
		"model": "movies.actor",
		"pk": 2450301,
		"fields": {
			"movie_id": 645541,
			"name": "Josiah Authier",
			"character": "Williams",
			"profile_photo": []
		}
	},
	{
		"model": "movies.actor",
		"pk": 17276,
		"fields": {
			"movie_id": 423204,
			"name": "Gerard Butler",
			"character": "Mike Banning",
			"profile_photo": "https://image.tmdb.org/t/p/original/wRKkVe5uugkx4KnmphBSjJUWPTo.jpg"
		}
	},
	{
		"model": "movies.actor",
		"pk": 192,
		"fields": {
			"movie_id": 423204,
			"name": "Morgan Freeman",
			"character": "Allan Trumbull",
			"profile_photo": "https://image.tmdb.org/t/p/original/oGJQhOpT8S1M56tvSsbEBePV5O1.jpg"
		}
	},
	{
		"model": "movies.actor",
		"pk": 9575,
		"fields": {
			"movie_id": 423204,
			"name": "Jada Pinkett Smith",
			"character": "FBI Agent Thompson",
			"profile_photo": "https://image.tmdb.org/t/p/original/Pb8KeGa4kTgJqS2ASoYvbNHbLr.jpg"
		}
	},
	{
		"model": "movies.actor",
		"pk": 129101,
		"fields": {
			"movie_id": 423204,
			"name": "Lance Reddick",
			"character": "Gentry",
			"profile_photo": "https://image.tmdb.org/t/p/original/5t4j7zvsjG5UyVxBJzly5OUMR3x.jpg"
		}
	},
	{
		"model": "movies.actor",
		"pk": 1462,
		"fields": {
			"movie_id": 423204,
			"name": "Tim Blake Nelson",
			"character": "Vice President Kirby",
			"profile_photo": "https://image.tmdb.org/t/p/original/dcfdSmVmklb1HXHbB9kySdrl9Nq.jpg"
		}
	},
	{
		"model": "movies.actor",
		"pk": 65510,
		"fields": {
			"movie_id": 568012,
			"name": "Mayumi Tanaka",
			"character": "Monkey D. Luffy (voice)",
			"profile_photo": "https://image.tmdb.org/t/p/original/rGUGLXCbdEb3KO7lRmLg0szNn4k.jpg"
		}
	},
	{
		"model": "movies.actor",
		"pk": 84507,
		"fields": {
			"movie_id": 568012,
			"name": "Kazuya Nakai",
			"character": "Roronoa Zoro (voice)",
			"profile_photo": "https://image.tmdb.org/t/p/original/hh4yhrzkDbf3HftDrFoV52SaVil.jpg"
		}
	},
	{
		"model": "movies.actor",
		"pk": 90133,
		"fields": {
			"movie_id": 568012,
			"name": "Akemi Okamura",
			"character": "Nami (voice)",
			"profile_photo": "https://image.tmdb.org/t/p/original/bqt1vYkQwRvCW8yMibiMWpZicGT.jpg"
		}
	},
	{
		"model": "movies.actor",
		"pk": 68472,
		"fields": {
			"movie_id": 568012,
			"name": "Kappei Yamaguchi",
			"character": "Usopp (voice)",
			"profile_photo": "https://image.tmdb.org/t/p/original/8QpMGuviKgXS9Kx3IbAJeQclQY.jpg"
		}
	},
	{
		"model": "movies.actor",
		"pk": 84505,
		"fields": {
			"movie_id": 568012,
			"name": "Hiroaki Hirata",
			"character": "Vinsmoke Sanji (voice)",
			"profile_photo": "https://image.tmdb.org/t/p/original/ynq8qnJyoivjf7qMnCVN2Z7eaKg.jpg"
		}
	},
	{
		"model": "movies.actor",
		"pk": 5530,
		"fields": {
			"movie_id": 474350,
			"name": "James McAvoy",
			"character": "Bill Denbrough",
			"profile_photo": "https://image.tmdb.org/t/p/original/oPIfGm3mf4lbmO5pWwMvfTt5BM1.jpg"
		}
	},
	{
		"model": "movies.actor",
		"pk": 83002,
		"fields": {
			"movie_id": 474350,
			"name": "Jessica Chastain",
			"character": "Beverly Marsh",
			"profile_photo": "https://image.tmdb.org/t/p/original/lodMzLKSdrPcBry6TdoDsMN3Vge.jpg"
		}
	},
	{
		"model": "movies.actor",
		"pk": 19278,
		"fields": {
			"movie_id": 474350,
			"name": "Bill Hader",
			"character": "Richie Tozier",
			"profile_photo": "https://image.tmdb.org/t/p/original/3Z5JsyLw7YTLZgpA3FAlLmFSN9F.jpg"
		}
	},
	{
		"model": "movies.actor",
		"pk": 5296,
		"fields": {
			"movie_id": 474350,
			"name": "James Ransone",
			"character": "Eddie Kaspbrak",
			"profile_photo": "https://image.tmdb.org/t/p/original/9j39UVIex7nIAOMaNqo0w9yJpSG.jpg"
		}
	},
	{
		"model": "movies.actor",
		"pk": 223901,
		"fields": {
			"movie_id": 474350,
			"name": "Jay Ryan",
			"character": "Ben Hanscom",
			"profile_photo": "https://image.tmdb.org/t/p/original/zMaGHqanBabmtj3GZcyFVOlcbLF.jpg"
		}
	},
	{
		"model": "movies.actor",
		"pk": 887,
		"fields": {
			"movie_id": 920,
			"name": "Owen Wilson",
			"character": "Lightning McQueen (voice)",
			"profile_photo": "https://image.tmdb.org/t/p/original/j7oYgvfDiO34VcFdSB7GhM2CSle.jpg"
		}
	},
	{
		"model": "movies.actor",
		"pk": 3636,
		"fields": {
			"movie_id": 920,
			"name": "Paul Newman",
			"character": "Doc Hudson (voice)",
			"profile_photo": "https://image.tmdb.org/t/p/original/xb9ycwwKn4K3BmzAWHe8bKqFDVr.jpg"
		}
	},
	{
		"model": "movies.actor",
		"pk": 5149,
		"fields": {
			"movie_id": 920,
			"name": "Bonnie Hunt",
			"character": "Sally Carrera (voice)",
			"profile_photo": "https://image.tmdb.org/t/p/original/uKAfrFRZYnHFAxw53Jldbs8yIZO.jpg"
		}
	},
	{
		"model": "movies.actor",
		"pk": 15897,
		"fields": {
			"movie_id": 920,
			"name": "Larry the Cable Guy",
			"character": "Mater (voice)",
			"profile_photo": "https://image.tmdb.org/t/p/original/9yGwJBveIvLidqJEQI4PRuKQhMr.jpg"
		}
	},
	{
		"model": "movies.actor",
		"pk": 4252,
		"fields": {
			"movie_id": 920,
			"name": "Tony Shalhoub",
			"character": "Luigi (voice)",
			"profile_photo": "https://image.tmdb.org/t/p/original/jXzlVxS8u64XEZUoNPiuhGcQXDW.jpg"
		}
	},
	{
		"model": "movies.actor",
		"pk": 2888,
		"fields": {
			"movie_id": 453405,
			"name": "Will Smith",
			"character": "Henry Brogen",
			"profile_photo": "https://image.tmdb.org/t/p/original/7XEzMCdMQffq8PrkLYjYb7QpIgW.jpg"
		}
	},
	{
		"model": "movies.actor",
		"pk": 17628,
		"fields": {
			"movie_id": 453405,
			"name": "Mary Elizabeth Winstead",
			"character": "Danny",
			"profile_photo": "https://image.tmdb.org/t/p/original/wXhBxYY2oQXINQClHvpow62mNsj.jpg"
		}
	},
	{
		"model": "movies.actor",
		"pk": 2296,
		"fields": {
			"movie_id": 453405,
			"name": "Clive Owen",
			"character": "Clay Verris",
			"profile_photo": "https://image.tmdb.org/t/p/original/fIfCVQiizAhmfJxVRjXQ8d8l6tO.jpg"
		}
	},
	{
		"model": "movies.actor",
		"pk": 30082,
		"fields": {
			"movie_id": 453405,
			"name": "Benedict Wong",
			"character": "Baron",
			"profile_photo": "https://image.tmdb.org/t/p/original/iBzJ8s7GqgtRfGH3q0Ep5OKnaGf.jpg"
		}
	},
	{
		"model": "movies.actor",
		"pk": 58643,
		"fields": {
			"movie_id": 453405,
			"name": "Linda Emond",
			"character": "Lassiter",
			"profile_photo": "https://image.tmdb.org/t/p/original/PjDT3zk5xAIFiJ1MaEJLtjdq5s.jpg"
		}
	},
	{
		"model": "movies.actor",
		"pk": 1892,
		"fields": {
			"movie_id": 359724,
			"name": "Matt Damon",
			"character": "Carroll Shelby",
			"profile_photo": "https://image.tmdb.org/t/p/original/elSlNgV8xVifsbHpFsqrPGxJToZ.jpg"
		}
	},
	{
		"model": "movies.actor",
		"pk": 3894,
		"fields": {
			"movie_id": 359724,
			"name": "Christian Bale",
			"character": "Ken Miles",
			"profile_photo": "https://image.tmdb.org/t/p/original/4xydbSbAutKqXJwXtKlTIVU9qXA.jpg"
		}
	},
	{
		"model": "movies.actor",
		"pk": 19498,
		"fields": {
			"movie_id": 359724,
			"name": "Jon Bernthal",
			"character": "Lee Iacocca",
			"profile_photo": "https://image.tmdb.org/t/p/original/jxTk3sSMqGkrqr5t1R7KfITXX4I.jpg"
		}
	},
	{
		"model": "movies.actor",
		"pk": 72638,
		"fields": {
			"movie_id": 359724,
			"name": "Tracy Letts",
			"character": "Henry Ford II",
			"profile_photo": "https://image.tmdb.org/t/p/original/lW2NSl9E2cCmqEm1RaG8h4o1Qsg.jpg"
		}
	},
	{
		"model": "movies.actor",
		"pk": 147056,
		"fields": {
			"movie_id": 359724,
			"name": "Caitriona Balfe",
			"character": "Mollie Miles",
			"profile_photo": "https://image.tmdb.org/t/p/original/dJXx9ILYKqpbki10LJHRvQPEvyi.jpg"
		}
	},
	{
		"model": "movies.actor",
		"pk": 67599,
		"fields": {
			"movie_id": 611207,
			"name": "Vanessa Hudgens",
			"character": "Brooke",
			"profile_photo": "https://image.tmdb.org/t/p/original/ssFXWN5li5OWJLgUoFlUDY0ZyPc.jpg"
		}
	},
	{
		"model": "movies.actor",
		"pk": 1711290,
		"fields": {
			"movie_id": 611207,
			"name": "Josh Whitehouse",
			"character": "Sir Cole Christopher Frederick Lyons of Norwich",
			"profile_photo": "https://image.tmdb.org/t/p/original/5blAQc7Va0RHNQWOzr7dLZOGZib.jpg"
		}
	},
	{
		"model": "movies.actor",
		"pk": 59192,
		"fields": {
			"movie_id": 611207,
			"name": "Emmanuelle Chriqui",
			"character": "Madison",
			"profile_photo": "https://image.tmdb.org/t/p/original/o5S7XasZR7GQZmjeDirQ2kfc1pQ.jpg"
		}
	},
	{
		"model": "movies.actor",
		"pk": 1510971,
		"fields": {
			"movie_id": 611207,
			"name": "Harry Jarvis",
			"character": "Sir Geoffrey",
			"profile_photo": "https://image.tmdb.org/t/p/original/7EvtlqhPUg9cjlaSAlNL0znNzwo.jpg"
		}
	},
	{
		"model": "movies.actor",
		"pk": 1225784,
		"fields": {
			"movie_id": 611207,
			"name": "Ella Kenion",
			"character": "Old Crone",
			"profile_photo": []
		}
	},
	{
		"model": "movies.actor",
		"pk": 1341,
		"fields": {
			"movie_id": 449924,
			"name": "Donnie Yen",
			"character": "Ip Man",
			"profile_photo": "https://image.tmdb.org/t/p/original/vlKBbOc0htUsDGvcxeULcFXDMRo.jpg"
		}
	},
	{
		"model": "movies.actor",
		"pk": 83633,
		"fields": {
			"movie_id": 449924,
			"name": "Vanness Wu",
			"character": "",
			"profile_photo": "https://image.tmdb.org/t/p/original/pFlm7iHEhXpzJ2QKbtk9EApqtnN.jpg"
		}
	},
	{
		"model": "movies.actor",
		"pk": 78110,
		"fields": {
			"movie_id": 449924,
			"name": "Scott Adkins",
			"character": "",
			"profile_photo": "https://image.tmdb.org/t/p/original/n1L8652hJAKi5l2sdrZ07oZJmos.jpg"
		}
	},
	{
		"model": "movies.actor",
		"pk": 1173223,
		"fields": {
			"movie_id": 449924,
			"name": "Danny Chan Kwok-Kwan",
			"character": "Bruce Lee",
			"profile_photo": "https://image.tmdb.org/t/p/original/hkHu1Z4EtN47bPwh6PlBIE3Jz76.jpg"
		}
	},
	{
		"model": "movies.actor",
		"pk": 1800792,
		"fields": {
			"movie_id": 449924,
			"name": "Wu Yue",
			"character": "",
			"profile_photo": "https://image.tmdb.org/t/p/original/hRePA3mh9mfAqX7SJ4rGxrNrxT7.jpg"
		}
	},
	{
		"model": "movies.actor",
		"pk": 56734,
		"fields": {
			"movie_id": 486589,
			"name": "Chloë Grace Moretz",
			"character": "Snow White (voice)",
			"profile_photo": "https://image.tmdb.org/t/p/original/sk6we3WfYppsx5KjMVzQGYEXpD2.jpg"
		}
	},
	{
		"model": "movies.actor",
		"pk": 237455,
		"fields": {
			"movie_id": 486589,
			"name": "Sam Claflin",
			"character": "Merlin (voice)",
			"profile_photo": "https://image.tmdb.org/t/p/original/8DVC5uMFX00G0sLIE0bBaF6nC3U.jpg"
		}
	},
	{
		"model": "movies.actor",
		"pk": 11150,
		"fields": {
			"movie_id": 486589,
			"name": "Gina Gershon",
			"character": "The Evil Queen (voice)",
			"profile_photo": "https://image.tmdb.org/t/p/original/7Y6WzhtQafT4zeOdWllxc1uf33b.jpg"
		}
	},
	{
		"model": "movies.actor",
		"pk": 161932,
		"fields": {
			"movie_id": 486589,
			"name": "Jim Rash",
			"character": "Prince Average (voice)",
			"profile_photo": "https://image.tmdb.org/t/p/original/cXat9HZ5ajQZsrAZ8xE4zIEVEcb.jpg"
		}
	},
	{
		"model": "movies.actor",
		"pk": 9657,
		"fields": {
			"movie_id": 486589,
			"name": "Patrick Warburton",
			"character": "Magic Mirror (voice)",
			"profile_photo": "https://image.tmdb.org/t/p/original/cq8zZ6YfBrq2k4F4aHYLSP9QOJS.jpg"
		}
	},
	{
		"model": "movies.actor",
		"pk": 1515478,
		"fields": {
			"movie_id": 420817,
			"name": "Mena Massoud",
			"character": "Aladdin",
			"profile_photo": "https://image.tmdb.org/t/p/original/yeaEd4P4kNlRkDqzunsQeh24rQm.jpg"
		}
	},
	{
		"model": "movies.actor",
		"pk": 240724,
		"fields": {
			"movie_id": 420817,
			"name": "Naomi Grace Scott",
			"character": "Jasmine",
			"profile_photo": "https://image.tmdb.org/t/p/original/d140yTWCle6rYUGE9GIVZVPaPng.jpg"
		}
	},
	{
		"model": "movies.actor",
		"pk": 2888,
		"fields": {
			"movie_id": 420817,
			"name": "Will Smith",
			"character": "Genie",
			"profile_photo": "https://image.tmdb.org/t/p/original/7XEzMCdMQffq8PrkLYjYb7QpIgW.jpg"
		}
	},
	{
		"model": "movies.actor",
		"pk": 935235,
		"fields": {
			"movie_id": 420817,
			"name": "Marwan Kenzari",
			"character": "Jafar",
			"profile_photo": "https://image.tmdb.org/t/p/original/k0qx65csI86rAFBR4Sal7phY3Vl.jpg"
		}
	},
	{
		"model": "movies.actor",
		"pk": 103330,
		"fields": {
			"movie_id": 420817,
			"name": "Navid Negahban",
			"character": "The Sultan",
			"profile_photo": "https://image.tmdb.org/t/p/original/cPsYncbHK7J76Sm4bc1rtgRh5qf.jpg"
		}
	},
	{
		"model": "movies.actor",
		"pk": 17881,
		"fields": {
			"movie_id": 508965,
			"name": "Jason Schwartzman",
			"character": "Jesper",
			"profile_photo": "https://image.tmdb.org/t/p/original/gCjMdmW1DiPAClHVl4zHEIffIsE.jpg"
		}
	},
	{
		"model": "movies.actor",
		"pk": 18999,
		"fields": {
			"movie_id": 508965,
			"name": "J.K. Simmons",
			"character": "Klaus",
			"profile_photo": "https://image.tmdb.org/t/p/original/jPoNW5fugs5h8AbcE7H5OBm04Tm.jpg"
		}
	},
	{
		"model": "movies.actor",
		"pk": 80591,
		"fields": {
			"movie_id": 508965,
			"name": "Rashida Jones",
			"character": "Alva",
			"profile_photo": "https://image.tmdb.org/t/p/original/jjp33eRM6oavyesW0UM6XBCxQSa.jpg"
		}
	},
	{
		"model": "movies.actor",
		"pk": 3234,
		"fields": {
			"movie_id": 508965,
			"name": "Joan Cusack",
			"character": "Mrs. Krum",
			"profile_photo": "https://image.tmdb.org/t/p/original/3jcrXcFYoSKEUvokzqrQ2UJGtw.jpg"
		}
	},
	{
		"model": "movies.actor",
		"pk": 77075,
		"fields": {
			"movie_id": 508965,
			"name": "Norm Macdonald",
			"character": "Captain Mogens",
			"profile_photo": "https://image.tmdb.org/t/p/original/pGOpdt9Xy9YO2nUEWgp8G89KC5r.jpg"
		}
	},
	{
		"model": "movies.actor",
		"pk": 1599422,
		"fields": {
			"movie_id": 476631,
			"name": "Erica Lindbeck",
			"character": "Barbie",
			"profile_photo": "https://image.tmdb.org/t/p/original/iJ7YNShDRF4YN2IP4UpNLdXVxED.jpg"
		}
	},
	{
		"model": "movies.actor",
		"pk": 1818585,
		"fields": {
			"movie_id": 476631,
			"name": "Claire Margaret Corlett",
			"character": "Stacie",
			"profile_photo": "https://image.tmdb.org/t/p/original/fvsGmLrb8cM7AGXBLj7xvKKodCu.jpg"
		}
	},
	{
		"model": "movies.actor",
		"pk": 569211,
		"fields": {
			"movie_id": 476631,
			"name": "Kazumi Evans",
			"character": "Skipper",
			"profile_photo": "https://image.tmdb.org/t/p/original/euNGNW2wcBG6LTWe8Nmtw0Q8f7F.jpg"
		}
	},
	{
		"model": "movies.actor",
		"pk": 1532532,
		"fields": {
			"movie_id": 476631,
			"name": "Alyssya Swales",
			"character": "Chelsea",
			"profile_photo": "https://image.tmdb.org/t/p/original/jK6lcWSA2ZepiLxOmUO1QPKjgQj.jpg"
		}
	},
	{
		"model": "movies.actor",
		"pk": 1799721,
		"fields": {
			"movie_id": 453075,
			"name": "Kim Tae-hun",
			"character": "Yong-jun",
			"profile_photo": "https://image.tmdb.org/t/p/original/3hcxyFZuxdKIV5RNTDcqLokm2qh.jpg"
		}
	},
	{
		"model": "movies.actor",
		"pk": 1799740,
		"fields": {
			"movie_id": 453075,
			"name": "Choi Jae-sung",
			"character": "Jae-sung",
			"profile_photo": "https://image.tmdb.org/t/p/original/qj3RubzIjCfohkzhSZWg01IRGg6.jpg"
		}
	},
	{
		"model": "movies.actor",
		"pk": 1365069,
		"fields": {
			"movie_id": 453075,
			"name": "Shin Won-ho",
			"character": "Tae-kyu",
			"profile_photo": "https://image.tmdb.org/t/p/original/rLE88b7BImoDY288rli1C5CHi3F.jpg"
		}
	},
	{
		"model": "movies.actor",
		"pk": 18918,
		"fields": {
			"movie_id": 384018,
			"name": "Dwayne Johnson",
			"character": "Luke Hobbs",
			"profile_photo": "https://image.tmdb.org/t/p/original/kuqFzlYMc2IrsOyPznMd1FroeGq.jpg"
		}
	},
	{
		"model": "movies.actor",
		"pk": 976,
		"fields": {
			"movie_id": 384018,
			"name": "Jason Statham",
			"character": "Deckard Shaw",
			"profile_photo": "https://image.tmdb.org/t/p/original/PhWiWgasncGWD9LdbsGcmxkV4r.jpg"
		}
	},
	{
		"model": "movies.actor",
		"pk": 17605,
		"fields": {
			"movie_id": 384018,
			"name": "Idris Elba",
			"character": "Brixton",
			"profile_photo": "https://image.tmdb.org/t/p/original/be1bVF7qGX91a6c5WeRPs5pKXln.jpg"
		}
	},
	{
		"model": "movies.actor",
		"pk": 556356,
		"fields": {
			"movie_id": 384018,
			"name": "Vanessa Kirby",
			"character": "Hattie Shaw",
			"profile_photo": "https://image.tmdb.org/t/p/original/9itJW9EjTS4tXHa02LusOgX8vdN.jpg"
		}
	},
	{
		"model": "movies.actor",
		"pk": 1222992,
		"fields": {
			"movie_id": 384018,
			"name": "Eiza González",
			"character": "Madame M",
			"profile_photo": "https://image.tmdb.org/t/p/original/2EpyDXqw1oyJnKayu2XshczjiBN.jpg"
		}
	},
	{
		"model": "movies.actor",
		"pk": 37917,
		"fields": {
			"movie_id": 458897,
			"name": "Kristen Stewart",
			"character": "Sabina Wilson",
			"profile_photo": "https://image.tmdb.org/t/p/original/j8bwiPbTwU7nMqLzXwieGobfL2D.jpg"
		}
	},
	{
		"model": "movies.actor",
		"pk": 240724,
		"fields": {
			"movie_id": 458897,
			"name": "Naomi Grace Scott",
			"character": "Elena Houghlin",
			"profile_photo": "https://image.tmdb.org/t/p/original/d140yTWCle6rYUGE9GIVZVPaPng.jpg"
		}
	},
	{
		"model": "movies.actor",
		"pk": 2092879,
		"fields": {
			"movie_id": 458897,
			"name": "Ella Balinska",
			"character": "Jane Kano",
			"profile_photo": "https://image.tmdb.org/t/p/original/xlCX9uilyLOu6zKrBNsdafzNYG1.jpg"
		}
	},
	{
		"model": "movies.actor",
		"pk": 9281,
		"fields": {
			"movie_id": 458897,
			"name": "Elizabeth Banks",
			"character": "Bosley",
			"profile_photo": "https://image.tmdb.org/t/p/original/w2RrVNLQa4ApXhpIgWTkpNVS2kd.jpg"
		}
	},
	{
		"model": "movies.actor",
		"pk": 17243,
		"fields": {
			"movie_id": 458897,
			"name": "Jonathan Tucker",
			"character": "Hodak",
			"profile_photo": "https://image.tmdb.org/t/p/original/jvJpYDbwmUTACw7Yn7PKOP6CdlJ.jpg"
		}
	},
	{
		"model": "movies.actor",
		"pk": 16483,
		"fields": {
			"movie_id": 522938,
			"name": "Sylvester Stallone",
			"character": "John Rambo",
			"profile_photo": "https://image.tmdb.org/t/p/original/gnmwOa46C2TP35N7ARSzboTdx2u.jpg"
		}
	},
	{
		"model": "movies.actor",
		"pk": 1442968,
		"fields": {
			"movie_id": 522938,
			"name": "Yvette Monreal",
			"character": "Gabrielle",
			"profile_photo": "https://image.tmdb.org/t/p/original/a10WhnArNlGod8RKgih1BX8DO9Q.jpg"
		}
	},
	{
		"model": "movies.actor",
		"pk": 59129,
		"fields": {
			"movie_id": 522938,
			"name": "Óscar Jaenada",
			"character": "Victor Martinez",
			"profile_photo": "https://image.tmdb.org/t/p/original/aOv6MLlApilNn21kyJhs66Lx3Ac.jpg"
		}
	},
	{
		"model": "movies.actor",
		"pk": 78994,
		"fields": {
			"movie_id": 522938,
			"name": "Sergio Peris-Mencheta",
			"character": "Hugo Martinez",
			"profile_photo": "https://image.tmdb.org/t/p/original/pdNIwIs0UCNEfZeUHVIcPvAVVuy.jpg"
		}
	},
	{
		"model": "movies.actor",
		"pk": 3627,
		"fields": {
			"movie_id": 522938,
			"name": "Paz Vega",
			"character": "Carmen Delgado",
			"profile_photo": "https://image.tmdb.org/t/p/original/9MJL1PNq9iVRFmlchusJTruzlj7.jpg"
		}
	},
	{
		"model": "movies.actor",
		"pk": 17743,
		"fields": {
			"movie_id": 640882,
			"name": "Miranda Cosgrove",
			"character": "",
			"profile_photo": "https://image.tmdb.org/t/p/original/xwJxbOTWJc1AKvC33v9PNsuYX6Q.jpg"
		}
	},
	{
		"model": "movies.actor",
		"pk": 61114,
		"fields": {
			"movie_id": 640882,
			"name": "Kate Walsh",
			"character": "Jackie Miller",
			"profile_photo": "https://image.tmdb.org/t/p/original/z2o4tml3ClbrcJ2ZYtqdtYJcsEY.jpg"
		}
	},
	{
		"model": "movies.actor",
		"pk": 4987,
		"fields": {
			"movie_id": 640882,
			"name": "Omar Epps",
			"character": "John Laine",
			"profile_photo": "https://image.tmdb.org/t/p/original/t4Qg5ANKK2idfOt4RzWzhiP7IEv.jpg"
		}
	},
	{
		"model": "movies.actor",
		"pk": 2464,
		"fields": {
			"movie_id": 640882,
			"name": "Angus Macfadyen",
			"character": "Dr. Richard Valin",
			"profile_photo": "https://image.tmdb.org/t/p/original/qTplz89WHXM4dGu0PVSarWEYHcO.jpg"
		}
	},
	{
		"model": "movies.actor",
		"pk": 536,
		"fields": {
			"movie_id": 640882,
			"name": "Jorja Fox",
			"character": "Diane Ures",
			"profile_photo": "https://image.tmdb.org/t/p/original/jq3W7EF5juYapLoA779QHmAbAGL.jpg"
		}
	},
	{
		"model": "movies.actor",
		"pk": 3223,
		"fields": {
			"movie_id": 299536,
			"name": "Robert Downey Jr.",
			"character": "Tony Stark / Iron Man",
			"profile_photo": "https://image.tmdb.org/t/p/original/1YjdSym1jTG7xjHSI0yGGWEsw5i.jpg"
		}
	},
	{
		"model": "movies.actor",
		"pk": 74568,
		"fields": {
			"movie_id": 299536,
			"name": "Chris Hemsworth",
			"character": "Thor Odinson",
			"profile_photo": "https://image.tmdb.org/t/p/original/lrhth7yK9p3vy6p7AabDUM1THKl.jpg"
		}
	},
	{
		"model": "movies.actor",
		"pk": 16828,
		"fields": {
			"movie_id": 299536,
			"name": "Chris Evans",
			"character": "Steve Rogers / Captain America",
			"profile_photo": "https://image.tmdb.org/t/p/original/7dUkkq1lK593XvOjunlUB11lKm1.jpg"
		}
	},
	{
		"model": "movies.actor",
		"pk": 103,
		"fields": {
			"movie_id": 299536,
			"name": "Mark Ruffalo",
			"character": "Bruce Banner / The Hulk",
			"profile_photo": "https://image.tmdb.org/t/p/original/z3dvKqMNDQWk3QLxzumloQVR0pv.jpg"
		}
	},
	{
		"model": "movies.actor",
		"pk": 1245,
		"fields": {
			"movie_id": 299536,
			"name": "Scarlett Johansson",
			"character": "Natasha Romanoff / Black Widow",
			"profile_photo": "https://image.tmdb.org/t/p/original/6NsMbJXRlDZuDzatN2akFdGuTvx.jpg"
		}
	},
	{
		"model": "movies.actor",
		"pk": 8784,
		"fields": {
			"movie_id": 546554,
			"name": "Daniel Craig",
			"character": "Detective Benoit Blanc",
			"profile_photo": "https://image.tmdb.org/t/p/original/vnfJWpeFKbjwfqcpRWoVPZIkltY.jpg"
		}
	},
	{
		"model": "movies.actor",
		"pk": 224513,
		"fields": {
			"movie_id": 546554,
			"name": "Ana de Armas",
			"character": "Marta Cabrera",
			"profile_photo": "https://image.tmdb.org/t/p/original/8nXpnukcdLTsTmJrHfwbLq2DUm9.jpg"
		}
	},
	{
		"model": "movies.actor",
		"pk": 16828,
		"fields": {
			"movie_id": 546554,
			"name": "Chris Evans",
			"character": "Ransom Drysdale",
			"profile_photo": "https://image.tmdb.org/t/p/original/7dUkkq1lK593XvOjunlUB11lKm1.jpg"
		}
	},
	{
		"model": "movies.actor",
		"pk": 1200864,
		"fields": {
			"movie_id": 546554,
			"name": "Lakeith Stanfield",
			"character": "Lieutenant Elliott",
			"profile_photo": "https://image.tmdb.org/t/p/original/5AykKpsH8DMxIm144ET7fVVTQfw.jpg"
		}
	},
	{
		"model": "movies.actor",
		"pk": 8944,
		"fields": {
			"movie_id": 546554,
			"name": "Jamie Lee Curtis",
			"character": "Linda Drysdale",
			"profile_photo": "https://image.tmdb.org/t/p/original/c4poMDwQ0nUj81m4WPriiv96ExZ.jpg"
		}
	},
	{
		"model": "movies.actor",
		"pk": 1027740,
		"fields": {
			"movie_id": 101411,
			"name": "Paco Tous",
			"character": "Antonio Tejero",
			"profile_photo": "https://image.tmdb.org/t/p/original/fl3tEdiIod0NpMMJv9uL7bQTokd.jpg"
		}
	},
	{
		"model": "movies.actor",
		"pk": 56468,
		"fields": {
			"movie_id": 101411,
			"name": "Mariano Venancio",
			"character": "Sabino Fernández Campos",
			"profile_photo": "https://image.tmdb.org/t/p/original/uVT79nEvsilJVsKE90xvQCHOv48.jpg"
		}
	},
	{
		"model": "movies.actor",
		"pk": 37580,
		"fields": {
			"movie_id": 101411,
			"name": "Juan Diego",
			"character": "Alfonso Armada",
			"profile_photo": "https://image.tmdb.org/t/p/original/lVPpxHGzxvs2ZPerGHpuHBMc8dz.jpg"
		}
	},
	{
		"model": "movies.actor",
		"pk": 51902,
		"fields": {
			"movie_id": 101411,
			"name": "Fernando Cayo",
			"character": "Juan Carlos",
			"profile_photo": "https://image.tmdb.org/t/p/original/sglfXHNFlzOBBLuRrbDkxghSW4H.jpg"
		}
	},
	{
		"model": "movies.actor",
		"pk": 1408413,
		"fields": {
			"movie_id": 101411,
			"name": "Juan Calot",
			"character": "",
			"profile_photo": "https://image.tmdb.org/t/p/original/yNpVeYWUuVu84c0gjRrK4kVH7QT.jpg"
		}
	},
	{
		"model": "movies.actor",
		"pk": 84497,
		"fields": {
			"movie_id": 559969,
			"name": "Aaron Paul",
			"character": "Jesse Pinkman",
			"profile_photo": "https://image.tmdb.org/t/p/original/u8UdsB9yenM4uHEjmce4nkBn48X.jpg"
		}
	},
	{
		"model": "movies.actor",
		"pk": 88124,
		"fields": {
			"movie_id": 559969,
			"name": "Jesse Plemons",
			"character": "Todd",
			"profile_photo": "https://image.tmdb.org/t/p/original/vfTsSy2pFkIlOE86ifhs6sXOtcg.jpg"
		}
	},
	{
		"model": "movies.actor",
		"pk": 82945,
		"fields": {
			"movie_id": 559969,
			"name": "Charles Baker",
			"character": "Skinny Pete",
			"profile_photo": "https://image.tmdb.org/t/p/original/yuRBqdgCh4OgTsfl2Xs4mC6PpnZ.jpg"
		}
	},
	{
		"model": "movies.actor",
		"pk": 191202,
		"fields": {
			"movie_id": 559969,
			"name": "Matt Jones",
			"character": "Badger Mayhew",
			"profile_photo": "https://image.tmdb.org/t/p/original/hGyN6Zz239gN6VP4hJbrIq9R6wd.jpg"
		}
	},
	{
		"model": "movies.actor",
		"pk": 209087,
		"fields": {
			"movie_id": 559969,
			"name": "Scott MacArthur",
			"character": "Neil",
			"profile_photo": "https://image.tmdb.org/t/p/original/xfbp7uWujYAqlgWHkwGGEmQKNgg.jpg"
		}
	},
	{
		"model": "movies.actor",
		"pk": 2,
		"fields": {
			"movie_id": 11,
			"name": "Mark Hamill",
			"character": "Luke Skywalker",
			"profile_photo": "https://image.tmdb.org/t/p/original/fk8OfdReNltKZqOk2TZgkofCUFq.jpg"
		}
	},
	{
		"model": "movies.actor",
		"pk": 3,
		"fields": {
			"movie_id": 11,
			"name": "Harrison Ford",
			"character": "Han Solo",
			"profile_photo": "https://image.tmdb.org/t/p/original/7CcoVFTogQgex2kJkXKMe8qHZrC.jpg"
		}
	},
	{
		"model": "movies.actor",
		"pk": 4,
		"fields": {
			"movie_id": 11,
			"name": "Carrie Fisher",
			"character": "Princess Leia Organa",
			"profile_photo": "https://image.tmdb.org/t/p/original/rfJtncHewKVnHjqpIZvjn24ESeC.jpg"
		}
	},
	{
		"model": "movies.actor",
		"pk": 5,
		"fields": {
			"movie_id": 11,
			"name": "Peter Cushing",
			"character": "Grand Moff Tarkin",
			"profile_photo": "https://image.tmdb.org/t/p/original/l0grZXcjqctESg7h6Jdp33pA3QG.jpg"
		}
	},
	{
		"model": "movies.actor",
		"pk": 12248,
		"fields": {
			"movie_id": 11,
			"name": "Alec Guinness",
			"character": "Obi-Wan \"Ben\" Kenobi",
			"profile_photo": "https://image.tmdb.org/t/p/original/4SzPZhHt2irzwPxLp42oFxbYwcW.jpg"
		}
	},
	{
		"model": "movies.actor",
		"pk": 1411561,
		"fields": {
			"movie_id": 484641,
			"name": "Sasha Luss",
			"character": "Anna",
			"profile_photo": "https://image.tmdb.org/t/p/original/vMLpPLLsVq6uphpAbfq55XrkMjf.jpg"
		}
	},
	{
		"model": "movies.actor",
		"pk": 15735,
		"fields": {
			"movie_id": 484641,
			"name": "Helen Mirren",
			"character": "Olga",
			"profile_photo": "https://image.tmdb.org/t/p/original/usuAZSSIYqBviO2eACXIiQpYpMW.jpg"
		}
	},
	{
		"model": "movies.actor",
		"pk": 114019,
		"fields": {
			"movie_id": 484641,
			"name": "Luke Evans",
			"character": "Alex Tchenkov",
			"profile_photo": "https://image.tmdb.org/t/p/original/1d31uDYub8TaLOPWfgX78OotduD.jpg"
		}
	},
	{
		"model": "movies.actor",
		"pk": 2037,
		"fields": {
			"movie_id": 484641,
			"name": "Cillian Murphy",
			"character": "Lenny Miller",
			"profile_photo": "https://image.tmdb.org/t/p/original/3DZAf9CwXmfV2HZOEdqeZAGTndV.jpg"
		}
	},
	{
		"model": "movies.actor",
		"pk": 2286738,
		"fields": {
			"movie_id": 484641,
			"name": "Lera Abova",
			"character": "Maud",
			"profile_photo": "https://image.tmdb.org/t/p/original/tZHb1fZkIuMR7T4cWM62MncEzpC.jpg"
		}
	},
	{
		"model": "movies.actor",
		"pk": 1443841,
		"fields": {
			"movie_id": 540247,
			"name": "Eric Paul Erickson",
			"character": "Marston",
			"profile_photo": []
		}
	},
	{
		"model": "movies.actor",
		"pk": 1354872,
		"fields": {
			"movie_id": 540247,
			"name": "Madison West Gill",
			"character": "Daize",
			"profile_photo": "https://image.tmdb.org/t/p/original/9TkE0Lh1lorD78RulDIuniv4oRx.jpg"
		}
	},
	{
		"model": "movies.actor",
		"pk": 1845702,
		"fields": {
			"movie_id": 540247,
			"name": "Ryan Budds",
			"character": "Corrigan",
			"profile_photo": []
		}
	},
	{
		"model": "movies.actor",
		"pk": 168874,
		"fields": {
			"movie_id": 540247,
			"name": "Doug Burch",
			"character": "Harris",
			"profile_photo": "https://image.tmdb.org/t/p/original/ylIeoYrK278PkJXUhbZkzW0soQI.jpg"
		}
	},
	{
		"model": "movies.actor",
		"pk": 95988,
		"fields": {
			"movie_id": 540247,
			"name": "Jonathan Nation",
			"character": "Flynn",
			"profile_photo": "https://image.tmdb.org/t/p/original/yhIRbVE9dWZlzCQFoe00fkA2Es4.jpg"
		}
	},
	{
		"model": "movies.actor",
		"pk": 1385600,
		"fields": {
			"movie_id": 487616,
			"name": "Noémie Merlant",
			"character": "Marie de Regnier",
			"profile_photo": "https://image.tmdb.org/t/p/original/qhzjer0eEsifUuqnGfbaSxZTtLo.jpg"
		}
	},
	{
		"model": "movies.actor",
		"pk": 143596,
		"fields": {
			"movie_id": 487616,
			"name": "Niels Schneider",
			"character": "Pierre Louÿs",
			"profile_photo": "https://image.tmdb.org/t/p/original/4DzGw1k7KhdgpiV8iYnOBhKuwIL.jpg"
		}
	},
	{
		"model": "movies.actor",
		"pk": 1159954,
		"fields": {
			"movie_id": 487616,
			"name": "Benjamin Lavernhe",
			"character": "Henri de Régnier",
			"profile_photo": "https://image.tmdb.org/t/p/original/gsQfHcYxlkp1tCoRphHYow2j4uG.jpg"
		}
	},
	{
		"model": "movies.actor",
		"pk": 1171510,
		"fields": {
			"movie_id": 487616,
			"name": "Camélia Jordana",
			"character": "Zohra Ben Brahim",
			"profile_photo": "https://image.tmdb.org/t/p/original/hNUOgsPRdI6lLAsC9jBB0l8sdNm.jpg"
		}
	},
	{
		"model": "movies.actor",
		"pk": 20577,
		"fields": {
			"movie_id": 487616,
			"name": "Amira Casar",
			"character": "Madame de Heredia",
			"profile_photo": "https://image.tmdb.org/t/p/original/50fLRb6xKqIrtTC5fBWTuxh1j82.jpg"
		}
	},
	{
		"model": "movies.actor",
		"pk": 1372369,
		"fields": {
			"movie_id": 567609,
			"name": "Samara Weaving",
			"character": "Grace",
			"profile_photo": "https://image.tmdb.org/t/p/original/7sHnBVEiJOzjdfzUHo9vvDLkoCH.jpg"
		}
	},
	{
		"model": "movies.actor",
		"pk": 1533,
		"fields": {
			"movie_id": 567609,
			"name": "Andie MacDowell",
			"character": "Becky Le Domas",
			"profile_photo": "https://image.tmdb.org/t/p/original/swiQfeUHHCFQWc8wFil00OKuzdw.jpg"
		}
	},
	{
		"model": "movies.actor",
		"pk": 225411,
		"fields": {
			"movie_id": 567609,
			"name": "Mark O'Brien",
			"character": "Alex Le Domas",
			"profile_photo": "https://image.tmdb.org/t/p/original/8ckgltvlife4BBJcBpHEQWXfQ9p.jpg"
		}
	},
	{
		"model": "movies.actor",
		"pk": 11702,
		"fields": {
			"movie_id": 567609,
			"name": "Adam Brody",
			"character": "Daniel Le Domas",
			"profile_photo": "https://image.tmdb.org/t/p/original/jeMhuu9Q81XJLIef1OU7NlcxRW0.jpg"
		}
	},
	{
		"model": "movies.actor",
		"pk": 15319,
		"fields": {
			"movie_id": 567609,
			"name": "Henry Czerny",
			"character": "Tony Le Domas",
			"profile_photo": "https://image.tmdb.org/t/p/original/zOWZzRmliKf9032IOOq0a3jXhVv.jpg"
		}
	},
	{
		"model": "movies.actor",
		"pk": 11701,
		"fields": {
			"movie_id": 420809,
			"name": "Angelina Jolie",
			"character": "Maleficent",
			"profile_photo": "https://image.tmdb.org/t/p/original/gD8jlGkQC8GBajulNlIzBK1YEO1.jpg"
		}
	},
	{
		"model": "movies.actor",
		"pk": 18050,
		"fields": {
			"movie_id": 420809,
			"name": "Elle Fanning",
			"character": "Princess Aurora",
			"profile_photo": "https://image.tmdb.org/t/p/original/e8CUyxQSE99y5IOfzSLtHC0B0Ch.jpg"
		}
	},
	{
		"model": "movies.actor",
		"pk": 1160,
		"fields": {
			"movie_id": 420809,
			"name": "Michelle Pfeiffer",
			"character": "Queen Ingrith",
			"profile_photo": "https://image.tmdb.org/t/p/original/oGUmQBU87QXAsnaGleYaAjAXSlj.jpg"
		}
	},
	{
		"model": "movies.actor",
		"pk": 1716493,
		"fields": {
			"movie_id": 420809,
			"name": "Harris Dickinson",
			"character": "Prince Phillip",
			"profile_photo": "https://image.tmdb.org/t/p/original/asiOPYCbcQYYG5SbxhBYH8xOIys.jpg"
		}
	},
	{
		"model": "movies.actor",
		"pk": 32987,
		"fields": {
			"movie_id": 420809,
			"name": "Sam Riley",
			"character": "Diaval",
			"profile_photo": "https://image.tmdb.org/t/p/original/4PfVxrZ4pXXZjTvMzf9UfGpV53K.jpg"
		}
	},
	{
		"model": "movies.actor",
		"pk": 40462,
		"fields": {
			"movie_id": 109445,
			"name": "Kristen Bell",
			"character": "Anna (voice)",
			"profile_photo": "https://image.tmdb.org/t/p/original/9DoDVUkoXhT3O2R1RymPlOfUryl.jpg"
		}
	},
	{
		"model": "movies.actor",
		"pk": 19394,
		"fields": {
			"movie_id": 109445,
			"name": "Idina Menzel",
			"character": "Elsa (voice)",
			"profile_photo": "https://image.tmdb.org/t/p/original/s2AjAX3qr0cZpfEdiEyYko9SGrZ.jpg"
		}
	},
	{
		"model": "movies.actor",
		"pk": 221611,
		"fields": {
			"movie_id": 109445,
			"name": "Jonathan Groff",
			"character": "Kristoff (voice)",
			"profile_photo": "https://image.tmdb.org/t/p/original/3kmnYKAzSc3Lp7iK5pcj97Hx9Cm.jpg"
		}
	},
	{
		"model": "movies.actor",
		"pk": 54415,
		"fields": {
			"movie_id": 109445,
			"name": "Josh Gad",
			"character": "Olaf (voice)",
			"profile_photo": "https://image.tmdb.org/t/p/original/oyEprEGF1aqWAqUZNx3yujJ9gPn.jpg"
		}
	},
	{
		"model": "movies.actor",
		"pk": 1188241,
		"fields": {
			"movie_id": 109445,
			"name": "Santino Fontana",
			"character": "Hans (voice)",
			"profile_photo": "https://image.tmdb.org/t/p/original/unQZPxiKxJt5TkOBRO6Retppc4i.jpg"
		}
	},
	{
		"model": "movies.actor",
		"pk": 973667,
		"fields": {
			"movie_id": 399579,
			"name": "Rosa Salazar",
			"character": "Alita",
			"profile_photo": "https://image.tmdb.org/t/p/original/rQZAi8uI74BGyi5fVN1ihOJ3qOa.jpg"
		}
	},
	{
		"model": "movies.actor",
		"pk": 27319,
		"fields": {
			"movie_id": 399579,
			"name": "Christoph Waltz",
			"character": "Dr. Dyson Ido",
			"profile_photo": "https://image.tmdb.org/t/p/original/2Hhztd4mUEV9Y25rfkXDwzL9QI9.jpg"
		}
	},
	{
		"model": "movies.actor",
		"pk": 6161,
		"fields": {
			"movie_id": 399579,
			"name": "Jennifer Connelly",
			"character": "Chiren",
			"profile_photo": "https://image.tmdb.org/t/p/original/mOVleZFCqMDugAXyyiJBq6LmSah.jpg"
		}
	},
	{
		"model": "movies.actor",
		"pk": 932967,
		"fields": {
			"movie_id": 399579,
			"name": "Mahershala Ali",
			"character": "Vector",
			"profile_photo": "https://image.tmdb.org/t/p/original/y9mf12rlZBlVJS6JYuCPpjTaLT6.jpg"
		}
	},
	{
		"model": "movies.actor",
		"pk": 1047649,
		"fields": {
			"movie_id": 399579,
			"name": "Ed Skrein",
			"character": "Zapan",
			"profile_photo": "https://image.tmdb.org/t/p/original/otPT5Ty6zy5jGBi3PQN6yC2FMel.jpg"
		}
	},
	{
		"model": "movies.actor",
		"pk": 20738,
		"fields": {
			"movie_id": 496243,
			"name": "Song Kang-ho",
			"character": "Kim Ki-taek",
			"profile_photo": "https://image.tmdb.org/t/p/original/joAXWwyjeed7qRDJ6jxSiMi7f5i.jpg"
		}
	},
	{
		"model": "movies.actor",
		"pk": 115290,
		"fields": {
			"movie_id": 496243,
			"name": "Lee Sun-kyun",
			"character": "Park Dong-ik",
			"profile_photo": "https://image.tmdb.org/t/p/original/nnwVLKIQPYoF88ohshnFfbSB0UW.jpg"
		}
	},
	{
		"model": "movies.actor",
		"pk": 556435,
		"fields": {
			"movie_id": 496243,
			"name": "Cho Yeo-jeong",
			"character": "Yeon-kyo",
			"profile_photo": "https://image.tmdb.org/t/p/original/5MgWM8pkUiYkj9MEaEpO0Ir1FD9.jpg"
		}
	},
	{
		"model": "movies.actor",
		"pk": 1255881,
		"fields": {
			"movie_id": 496243,
			"name": "Choi Woo-shik",
			"character": "Ki-woo",
			"profile_photo": "https://image.tmdb.org/t/p/original/qy2SEScTNOjtcjm7UafbIlXMqbG.jpg"
		}
	},
	{
		"model": "movies.actor",
		"pk": 1442583,
		"fields": {
			"movie_id": 496243,
			"name": "Park So-dam",
			"character": "Ki-jung",
			"profile_photo": "https://image.tmdb.org/t/p/original/uWppIvypWODMjCxiGDWX92y86ci.jpg"
		}
	},
	{
		"model": "movies.actor",
		"pk": 6384,
		"fields": {
			"movie_id": 458156,
			"name": "Keanu Reeves",
			"character": "John Wick",
			"profile_photo": "https://image.tmdb.org/t/p/original/bOlYWhVuOiU6azC4Bw6zlXZ5QTC.jpg"
		}
	},
	{
		"model": "movies.actor",
		"pk": 4587,
		"fields": {
			"movie_id": 458156,
			"name": "Halle Berry",
			"character": "Sofia",
			"profile_photo": "https://image.tmdb.org/t/p/original/AmCXHowNbUXpNf41dNrxNB0naM2.jpg"
		}
	},
	{
		"model": "movies.actor",
		"pk": 6972,
		"fields": {
			"movie_id": 458156,
			"name": "Ian McShane",
			"character": "Winston",
			"profile_photo": "https://image.tmdb.org/t/p/original/pY9ud4BJwHekNiO4MMItPbgkdAy.jpg"
		}
	},
	{
		"model": "movies.actor",
		"pk": 2975,
		"fields": {
			"movie_id": 458156,
			"name": "Laurence Fishburne",
			"character": "Bowery King",
			"profile_photo": "https://image.tmdb.org/t/p/original/8suOhUmPbfKqDQ17jQ1Gy0mI3P4.jpg"
		}
	},
	{
		"model": "movies.actor",
		"pk": 18702,
		"fields": {
			"movie_id": 458156,
			"name": "Mark Dacascos",
			"character": "Zero",
			"profile_photo": "https://image.tmdb.org/t/p/original/rPVgMthfpUpPAsHj5RRS0Gk0mHM.jpg"
		}
	},
	{
		"model": "movies.actor",
		"pk": 6384,
		"fields": {
			"movie_id": 245891,
			"name": "Keanu Reeves",
			"character": "John Wick",
			"profile_photo": "https://image.tmdb.org/t/p/original/bOlYWhVuOiU6azC4Bw6zlXZ5QTC.jpg"
		}
	},
	{
		"model": "movies.actor",
		"pk": 6283,
		"fields": {
			"movie_id": 245891,
			"name": "Michael Nyqvist",
			"character": "Viggo Tarasov",
			"profile_photo": "https://image.tmdb.org/t/p/original/bDjPDDiSna8FN5rqHdheg2wIYYo.jpg"
		}
	},
	{
		"model": "movies.actor",
		"pk": 71586,
		"fields": {
			"movie_id": 245891,
			"name": "Alfie Allen",
			"character": "Iosef Tarasov",
			"profile_photo": "https://image.tmdb.org/t/p/original/4q6yzSMi8Q5XeIn5A1yUD1tEfwq.jpg"
		}
	},
	{
		"model": "movies.actor",
		"pk": 5293,
		"fields": {
			"movie_id": 245891,
			"name": "Willem Dafoe",
			"character": "Marcus",
			"profile_photo": "https://image.tmdb.org/t/p/original/xM5lhOR5tWWdIlFpBDeZJx9opIP.jpg"
		}
	},
	{
		"model": "movies.actor",
		"pk": 6972,
		"fields": {
			"movie_id": 245891,
			"name": "Ian McShane",
			"character": "Winston",
			"profile_photo": "https://image.tmdb.org/t/p/original/pY9ud4BJwHekNiO4MMItPbgkdAy.jpg"
		}
	},
	{
		"model": "movies.actor",
		"pk": 5530,
		"fields": {
			"movie_id": 246655,
			"name": "James McAvoy",
			"character": "Charles Xavier / Professor X",
			"profile_photo": "https://image.tmdb.org/t/p/original/oPIfGm3mf4lbmO5pWwMvfTt5BM1.jpg"
		}
	},
	{
		"model": "movies.actor",
		"pk": 17288,
		"fields": {
			"movie_id": 246655,
			"name": "Michael Fassbender",
			"character": "Erik Lehnsherr / Magneto",
			"profile_photo": "https://image.tmdb.org/t/p/original/oexNPLumoFpazzzUqzBSDDYiUg1.jpg"
		}
	},
	{
		"model": "movies.actor",
		"pk": 72129,
		"fields": {
			"movie_id": 246655,
			"name": "Jennifer Lawrence",
			"character": "Raven Darkholme / Mystique",
			"profile_photo": "https://image.tmdb.org/t/p/original/naZyy9IqAQDaAbr1kYShLdg6aPR.jpg"
		}
	},
	{
		"model": "movies.actor",
		"pk": 3292,
		"fields": {
			"movie_id": 246655,
			"name": "Nicholas Hoult",
			"character": "Hank McCoy / Beast",
			"profile_photo": "https://image.tmdb.org/t/p/original/h1gXgpuXERZTVhxMdjT7uvXIyq6.jpg"
		}
	},
	{
		"model": "movies.actor",
		"pk": 25072,
		"fields": {
			"movie_id": 246655,
			"name": "Oscar Isaac",
			"character": "En Sabah Nur / Apocalypse",
			"profile_photo": "https://image.tmdb.org/t/p/original/cY6ail3ebXDx9FCoZMgVGAbmBus.jpg"
		}
	},
	{
		"model": "movies.actor",
		"pk": 1428070,
		"fields": {
			"movie_id": 499701,
			"name": "Isabela Moner",
			"character": "Dora",
			"profile_photo": "https://image.tmdb.org/t/p/original/cQlaWpBzyPx4p6PDz0cr1Y0DrWY.jpg"
		}
	},
	{
		"model": "movies.actor",
		"pk": 11160,
		"fields": {
			"movie_id": 499701,
			"name": "Danny Trejo",
			"character": "Boots the Monkey (voice)",
			"profile_photo": "https://image.tmdb.org/t/p/original/7b8cDfrmeheQbgryfCm7MeJOxxM.jpg"
		}
	},
	{
		"model": "movies.actor",
		"pk": 1826682,
		"fields": {
			"movie_id": 499701,
			"name": "Jeffrey Wahlberg",
			"character": "Diego",
			"profile_photo": "https://image.tmdb.org/t/p/original/qQPYzh9ndleKqqFhpVMHqJfp8By.jpg"
		}
	},
	{
		"model": "movies.actor",
		"pk": 1121,
		"fields": {
			"movie_id": 499701,
			"name": "Benicio del Toro",
			"character": "Swiper the Fox (voice)",
			"profile_photo": "https://image.tmdb.org/t/p/original/cbkXDtNDFYHKsyQzqvzxjn7F7rX.jpg"
		}
	},
	{
		"model": "movies.actor",
		"pk": 239574,
		"fields": {
			"movie_id": 499701,
			"name": "Eugenio Derbez",
			"character": "Alejandro Gutierrez",
			"profile_photo": "https://image.tmdb.org/t/p/original/qbdFijrdgGKc4QKL6rL9eh6zJOP.jpg"
		}
	},
	{
		"model": "movies.actor",
		"pk": 3894,
		"fields": {
			"movie_id": 155,
			"name": "Christian Bale",
			"character": "Bruce Wayne / Batman",
			"profile_photo": "https://image.tmdb.org/t/p/original/4xydbSbAutKqXJwXtKlTIVU9qXA.jpg"
		}
	},
	{
		"model": "movies.actor",
		"pk": 3895,
		"fields": {
			"movie_id": 155,
			"name": "Michael Caine",
			"character": "Alfred Pennyworth",
			"profile_photo": "https://image.tmdb.org/t/p/original/fx6vcV7iTo2SNywQRPfh6v62wRR.jpg"
		}
	},
	{
		"model": "movies.actor",
		"pk": 1810,
		"fields": {
			"movie_id": 155,
			"name": "Heath Ledger",
			"character": "Joker",
			"profile_photo": "https://image.tmdb.org/t/p/original/nMwBqKKbd3OxmfD5mkShvFk9yY6.jpg"
		}
	},
	{
		"model": "movies.actor",
		"pk": 64,
		"fields": {
			"movie_id": 155,
			"name": "Gary Oldman",
			"character": "Commissioner James Gordon",
			"profile_photo": "https://image.tmdb.org/t/p/original/zvofPivWI5FASkmimoy3i8HPoDw.jpg"
		}
	},
	{
		"model": "movies.actor",
		"pk": 6383,
		"fields": {
			"movie_id": 155,
			"name": "Aaron Eckhart",
			"character": "Harvey Dent / Two-Face",
			"profile_photo": "https://image.tmdb.org/t/p/original/aRSofX2rMpOhPanB9Wh7veYmFn4.jpg"
		}
	},
	{
		"model": "movies.actor",
		"pk": 1047649,
		"fields": {
			"movie_id": 522162,
			"name": "Ed Skrein",
			"character": "Lieutenant Richard 'Dick' Best",
			"profile_photo": "https://image.tmdb.org/t/p/original/otPT5Ty6zy5jGBi3PQN6yC2FMel.jpg"
		}
	},
	{
		"model": "movies.actor",
		"pk": 17178,
		"fields": {
			"movie_id": 522162,
			"name": "Patrick Wilson",
			"character": "Rear Admiral Edwin T. Layton",
			"profile_photo": "https://image.tmdb.org/t/p/original/djhTpbOvrfdDsWZFFintj2Uv47a.jpg"
		}
	},
	{
		"model": "movies.actor",
		"pk": 967781,
		"fields": {
			"movie_id": 522162,
			"name": "Luke Kleintank",
			"character": "Lieutenant Clarence Earle Dickinson",
			"profile_photo": "https://image.tmdb.org/t/p/original/vIS6KZfeOeaZzTA2hhV6gVU43jA.jpg"
		}
	},
	{
		"model": "movies.actor",
		"pk": 114019,
		"fields": {
			"movie_id": 522162,
			"name": "Luke Evans",
			"character": "Commander Wade McClusky",
			"profile_photo": "https://image.tmdb.org/t/p/original/1d31uDYub8TaLOPWfgX78OotduD.jpg"
		}
	},
	{
		"model": "movies.actor",
		"pk": 57755,
		"fields": {
			"movie_id": 522162,
			"name": "Woody Harrelson",
			"character": "Admiral Chester W. Nimitz",
			"profile_photo": "https://image.tmdb.org/t/p/original/1ecdooAHICUhCZKKEKlFtccEmTU.jpg"
		}
	},
	{
		"model": "movies.actor",
		"pk": 3223,
		"fields": {
			"movie_id": 299534,
			"name": "Robert Downey Jr.",
			"character": "Tony Stark / Iron Man",
			"profile_photo": "https://image.tmdb.org/t/p/original/1YjdSym1jTG7xjHSI0yGGWEsw5i.jpg"
		}
	},
	{
		"model": "movies.actor",
		"pk": 16828,
		"fields": {
			"movie_id": 299534,
			"name": "Chris Evans",
			"character": "Steve Rogers / Captain America",
			"profile_photo": "https://image.tmdb.org/t/p/original/7dUkkq1lK593XvOjunlUB11lKm1.jpg"
		}
	},
	{
		"model": "movies.actor",
		"pk": 103,
		"fields": {
			"movie_id": 299534,
			"name": "Mark Ruffalo",
			"character": "Bruce Banner / Hulk",
			"profile_photo": "https://image.tmdb.org/t/p/original/z3dvKqMNDQWk3QLxzumloQVR0pv.jpg"
		}
	},
	{
		"model": "movies.actor",
		"pk": 74568,
		"fields": {
			"movie_id": 299534,
			"name": "Chris Hemsworth",
			"character": "Thor Odinson",
			"profile_photo": "https://image.tmdb.org/t/p/original/lrhth7yK9p3vy6p7AabDUM1THKl.jpg"
		}
	},
	{
		"model": "movies.actor",
		"pk": 1245,
		"fields": {
			"movie_id": 299534,
			"name": "Scarlett Johansson",
			"character": "Natasha Romanoff / Black Widow",
			"profile_photo": "https://image.tmdb.org/t/p/original/6NsMbJXRlDZuDzatN2akFdGuTvx.jpg"
		}
	},
	{
		"model": "movies.actor",
		"pk": 380,
		"fields": {
			"movie_id": 398978,
			"name": "Robert De Niro",
			"character": "Frank 'The Irishman' Sheeran",
			"profile_photo": "https://image.tmdb.org/t/p/original/8Bgdfv1oN9Mw0YuMHP6fw8KzDkc.jpg"
		}
	},
	{
		"model": "movies.actor",
		"pk": 1158,
		"fields": {
			"movie_id": 398978,
			"name": "Al Pacino",
			"character": "Jimmy Hoffa",
			"profile_photo": "https://image.tmdb.org/t/p/original/p1kKeR73oNXfIIuYhlCa29KOOmq.jpg"
		}
	},
	{
		"model": "movies.actor",
		"pk": 4517,
		"fields": {
			"movie_id": 398978,
			"name": "Joe Pesci",
			"character": "Russell Bufalino",
			"profile_photo": "https://image.tmdb.org/t/p/original/4zidewFE0x8OBlW0RjEKlkhw4lr.jpg"
		}
	},
	{
		"model": "movies.actor",
		"pk": 1037,
		"fields": {
			"movie_id": 398978,
			"name": "Harvey Keitel",
			"character": "Angelo Bruno",
			"profile_photo": "https://image.tmdb.org/t/p/original/f4fjeWB4TrT1gOOBGgFVe9otC0t.jpg"
		}
	},
	{
		"model": "movies.actor",
		"pk": 88124,
		"fields": {
			"movie_id": 398978,
			"name": "Jesse Plemons",
			"character": "Chuckie O'Brien",
			"profile_photo": "https://image.tmdb.org/t/p/original/vfTsSy2pFkIlOE86ifhs6sXOtcg.jpg"
		}
	},
	{
		"model": "movies.actor",
		"pk": 31,
		"fields": {
			"movie_id": 501907,
			"name": "Tom Hanks",
			"character": "Fred Rogers",
			"profile_photo": "https://image.tmdb.org/t/p/original/xxPMucou2wRDxLrud8i2D4dsywh.jpg"
		}
	},
	{
		"model": "movies.actor",
		"pk": 29528,
		"fields": {
			"movie_id": 501907,
			"name": "Matthew Rhys",
			"character": "Lloyd Vogel",
			"profile_photo": "https://image.tmdb.org/t/p/original/zDs03IefU7dX3ZnGVJPu1sOc1Vi.jpg"
		}
	},
	{
		"model": "movies.actor",
		"pk": 2955,
		"fields": {
			"movie_id": 501907,
			"name": "Chris Cooper",
			"character": "Jerry Vogel",
			"profile_photo": "https://image.tmdb.org/t/p/original/ytZY7YofdiAZyiyr4NyiB77lwwQ.jpg"
		}
	},
	{
		"model": "movies.actor",
		"pk": 155228,
		"fields": {
			"movie_id": 501907,
			"name": "Susan Kelechi Watson",
			"character": "Andrea Vogel",
			"profile_photo": "https://image.tmdb.org/t/p/original/yjvuD4RbT5fsxa6qa0Tp83Nzjex.jpg"
		}
	},
	{
		"model": "movies.actor",
		"pk": 15029,
		"fields": {
			"movie_id": 501907,
			"name": "Enrico Colantoni",
			"character": "Bill Isler",
			"profile_photo": "https://image.tmdb.org/t/p/original/yxxy8IrGRwnRPbLmgyfwF26Feve.jpg"
		}
	},
	{
		"model": "movies.actor",
		"pk": 10980,
		"fields": {
			"movie_id": 671,
			"name": "Daniel Radcliffe",
			"character": "Harry Potter",
			"profile_photo": "https://image.tmdb.org/t/p/original/kMSMa5tR43TLMR14ahU1neFVytz.jpg"
		}
	},
	{
		"model": "movies.actor",
		"pk": 10989,
		"fields": {
			"movie_id": 671,
			"name": "Rupert Grint",
			"character": "Ron Weasley",
			"profile_photo": "https://image.tmdb.org/t/p/original/dFVVJufva2zUSP6WS0pFfR7g8uN.jpg"
		}
	},
	{
		"model": "movies.actor",
		"pk": 10990,
		"fields": {
			"movie_id": 671,
			"name": "Emma Watson",
			"character": "Hermione Granger",
			"profile_photo": "https://image.tmdb.org/t/p/original/s77hUycSJ4x8RJWHDC9WPgotgxE.jpg"
		}
	},
	{
		"model": "movies.actor",
		"pk": 194,
		"fields": {
			"movie_id": 671,
			"name": "Richard Harris",
			"character": "Albus Dumbledore",
			"profile_photo": "https://image.tmdb.org/t/p/original/51wDHVFNqrYgvUBMOcACAt4sJU9.jpg"
		}
	},
	{
		"model": "movies.actor",
		"pk": 10993,
		"fields": {
			"movie_id": 671,
			"name": "Tom Felton",
			"character": "Draco Malfoy",
			"profile_photo": "https://image.tmdb.org/t/p/original/5hb2kKBYhpQRyWslJWzaDr5G1op.jpg"
		}
	},
	{
		"model": "movies.actor",
		"pk": 73457,
		"fields": {
			"movie_id": 283995,
			"name": "Chris Pratt",
			"character": "Peter Quill / Star-Lord",
			"profile_photo": "https://image.tmdb.org/t/p/original/gXKyT1YU5RWWPaE1je3ht58eUZr.jpg"
		}
	},
	{
		"model": "movies.actor",
		"pk": 8691,
		"fields": {
			"movie_id": 283995,
			"name": "Zoe Saldana",
			"character": "Gamora",
			"profile_photo": "https://image.tmdb.org/t/p/original/ofNrWiA2KDdqiNxFTLp51HcXUlp.jpg"
		}
	},
	{
		"model": "movies.actor",
		"pk": 543530,
		"fields": {
			"movie_id": 283995,
			"name": "Dave Bautista",
			"character": "Drax the Destroyer",
			"profile_photo": "https://image.tmdb.org/t/p/original/oZDL1VprkUEFhOtG5WcVjudj5ks.jpg"
		}
	},
	{
		"model": "movies.actor",
		"pk": 12835,
		"fields": {
			"movie_id": 283995,
			"name": "Vin Diesel",
			"character": "Baby Groot (voice)",
			"profile_photo": "https://image.tmdb.org/t/p/original/3RdYMTLoL1X16djGF52cFtJovDT.jpg"
		}
	},
	{
		"model": "movies.actor",
		"pk": 51329,
		"fields": {
			"movie_id": 283995,
			"name": "Bradley Cooper",
			"character": "Rocket (voice)",
			"profile_photo": "https://image.tmdb.org/t/p/original/nzvYJQSlKKTLZXg3QYp3MG1TCaF.jpg"
		}
	},
	{
		"model": "movies.actor",
		"pk": 31,
		"fields": {
			"movie_id": 301528,
			"name": "Tom Hanks",
			"character": "Woody (voice)",
			"profile_photo": "https://image.tmdb.org/t/p/original/xxPMucou2wRDxLrud8i2D4dsywh.jpg"
		}
	},
	{
		"model": "movies.actor",
		"pk": 12898,
		"fields": {
			"movie_id": 301528,
			"name": "Tim Allen",
			"character": "Buzz Lightyear (voice)",
			"profile_photo": "https://image.tmdb.org/t/p/original/84VfGVV4A9C6Rb0pgsCvxSVqnX.jpg"
		}
	},
	{
		"model": "movies.actor",
		"pk": 8873,
		"fields": {
			"movie_id": 301528,
			"name": "Annie Potts",
			"character": "Bo Peep (voice)",
			"profile_photo": "https://image.tmdb.org/t/p/original/hWIzkAH7jkSkxBfwdudxbSPxeno.jpg"
		}
	},
	{
		"model": "movies.actor",
		"pk": 3234,
		"fields": {
			"movie_id": 301528,
			"name": "Joan Cusack",
			"character": "Jessie (voice)",
			"profile_photo": "https://image.tmdb.org/t/p/original/3jcrXcFYoSKEUvokzqrQ2UJGtw.jpg"
		}
	},
	{
		"model": "movies.actor",
		"pk": 25147,
		"fields": {
			"movie_id": 301528,
			"name": "Tony Hale",
			"character": "Forky (voice)",
			"profile_photo": "https://image.tmdb.org/t/p/original/ar4uapp4w5wMkThZcqWUNMSTO8z.jpg"
		}
	},
	{
		"model": "movies.actor",
		"pk": 85,
		"fields": {
			"movie_id": 22,
			"name": "Johnny Depp",
			"character": "Captain Jack Sparrow",
			"profile_photo": "https://image.tmdb.org/t/p/original/kbWValANhZI8rbWZXximXuMN4UN.jpg"
		}
	},
	{
		"model": "movies.actor",
		"pk": 118,
		"fields": {
			"movie_id": 22,
			"name": "Geoffrey Rush",
			"character": "Captain Hector Barbossa",
			"profile_photo": "https://image.tmdb.org/t/p/original/npXFjaFQzBNroCEPllGPTZ5IisA.jpg"
		}
	},
	{
		"model": "movies.actor",
		"pk": 114,
		"fields": {
			"movie_id": 22,
			"name": "Orlando Bloom",
			"character": "Will Turner",
			"profile_photo": "https://image.tmdb.org/t/p/original/kKWJlX2tcjqceSfUxnV7Jle5Kt.jpg"
		}
	},
	{
		"model": "movies.actor",
		"pk": 116,
		"fields": {
			"movie_id": 22,
			"name": "Keira Knightley",
			"character": "Elizabeth Swann",
			"profile_photo": "https://image.tmdb.org/t/p/original/8GaYprIb8GlljllLnZtQyIZ7thU.jpg"
		}
	},
	{
		"model": "movies.actor",
		"pk": 1709,
		"fields": {
			"movie_id": 22,
			"name": "Jack Davenport",
			"character": "Commodore James Norrington",
			"profile_photo": "https://image.tmdb.org/t/p/original/qxM6XdLmZ6pKkQV7uVwgu7MLcfV.jpg"
		}
	},
	{
		"model": "movies.actor",
		"pk": 1100,
		"fields": {
			"movie_id": 87101,
			"name": "Arnold Schwarzenegger",
			"character": "The Terminator",
			"profile_photo": "https://image.tmdb.org/t/p/original/dUAFC9E1oVTDKFXCYcetPuOMXYA.jpg"
		}
	},
	{
		"model": "movies.actor",
		"pk": 76512,
		"fields": {
			"movie_id": 87101,
			"name": "Jason Clarke",
			"character": "John Connor",
			"profile_photo": "https://image.tmdb.org/t/p/original/k0wyfdMPh6TSaDKkrreuQIfg1sr.jpg"
		}
	},
	{
		"model": "movies.actor",
		"pk": 1223786,
		"fields": {
			"movie_id": 87101,
			"name": "Emilia Clarke",
			"character": "Sarah Connor",
			"profile_photo": "https://image.tmdb.org/t/p/original/g6jjDO1vW9K28jzo5z3q9xnZCTE.jpg"
		}
	},
	{
		"model": "movies.actor",
		"pk": 224181,
		"fields": {
			"movie_id": 87101,
			"name": "Jai Courtney",
			"character": "Kyle Reese",
			"profile_photo": "https://image.tmdb.org/t/p/original/yJJz9PIrVWnSdfAEOrfhevxNbLO.jpg"
		}
	},
	{
		"model": "movies.actor",
		"pk": 18999,
		"fields": {
			"movie_id": 87101,
			"name": "J.K. Simmons",
			"character": "Detective O'Brien",
			"profile_photo": "https://image.tmdb.org/t/p/original/jPoNW5fugs5h8AbcE7H5OBm04Tm.jpg"
		}
	},
	{
		"model": "movies.actor",
		"pk": 117642,
		"fields": {
			"movie_id": 297802,
			"name": "Jason Momoa",
			"character": "Arthur Curry / Aquaman",
			"profile_photo": "https://image.tmdb.org/t/p/original/tTONqzQuAnuMlfM5E0nU9RWukOE.jpg"
		}
	},
	{
		"model": "movies.actor",
		"pk": 55085,
		"fields": {
			"movie_id": 297802,
			"name": "Amber Heard",
			"character": "Mera",
			"profile_photo": "https://image.tmdb.org/t/p/original/ft4ACLVFBXaOotbicBLm1fODyZr.jpg"
		}
	},
	{
		"model": "movies.actor",
		"pk": 5293,
		"fields": {
			"movie_id": 297802,
			"name": "Willem Dafoe",
			"character": "Nuidis Vulko",
			"profile_photo": "https://image.tmdb.org/t/p/original/xM5lhOR5tWWdIlFpBDeZJx9opIP.jpg"
		}
	},
	{
		"model": "movies.actor",
		"pk": 17178,
		"fields": {
			"movie_id": 297802,
			"name": "Patrick Wilson",
			"character": "King Orm Marius / Ocean Master",
			"profile_photo": "https://image.tmdb.org/t/p/original/djhTpbOvrfdDsWZFFintj2Uv47a.jpg"
		}
	},
	{
		"model": "movies.actor",
		"pk": 2227,
		"fields": {
			"movie_id": 297802,
			"name": "Nicole Kidman",
			"character": "Atlanna",
			"profile_photo": "https://image.tmdb.org/t/p/original/lfW2cDigTcvuoe4k6UfCdGVE1R6.jpg"
		}
	},
	{
		"model": "movies.actor",
		"pk": 1008607,
		"fields": {
			"movie_id": 480105,
			"name": "Sophie Nélisse",
			"character": "Mia",
			"profile_photo": "https://image.tmdb.org/t/p/original/qDXt4dEgiVNz8sNOc149aEV8stJ.jpg"
		}
	},
	{
		"model": "movies.actor",
		"pk": 1931204,
		"fields": {
			"movie_id": 480105,
			"name": "Corinne Foxx",
			"character": "Sasha",
			"profile_photo": "https://image.tmdb.org/t/p/original/vGBkZDxLe1M43modBgILAJezRvI.jpg"
		}
	},
	{
		"model": "movies.actor",
		"pk": 2192533,
		"fields": {
			"movie_id": 480105,
			"name": "Sistine Rose Stallone",
			"character": "Nicole",
			"profile_photo": "https://image.tmdb.org/t/p/original/siVTiYctwrvOutwWj01bT1SoVS1.jpg"
		}
	},
	{
		"model": "movies.actor",
		"pk": 1213395,
		"fields": {
			"movie_id": 480105,
			"name": "Brianne Tju",
			"character": "Alexa",
			"profile_photo": "https://image.tmdb.org/t/p/original/uqWcOPWZb45Ae28iE9IUeLHJjEi.jpg"
		}
	},
	{
		"model": "movies.actor",
		"pk": 1469128,
		"fields": {
			"movie_id": 480105,
			"name": "Brec Bassinger",
			"character": "Catherine",
			"profile_photo": "https://image.tmdb.org/t/p/original/ggGaeipC6rPreZFPjqIeVZs5ZlX.jpg"
		}
	},
	{
		"model": "movies.actor",
		"pk": 1001657,
		"fields": {
			"movie_id": 320288,
			"name": "Sophie Turner",
			"character": "Jean Grey / Dark Phoenix",
			"profile_photo": "https://image.tmdb.org/t/p/original/kZWYgD1T7ReZTt0al5gfkoviXG7.jpg"
		}
	},
	{
		"model": "movies.actor",
		"pk": 5530,
		"fields": {
			"movie_id": 320288,
			"name": "James McAvoy",
			"character": "Charles Xavier / Professor X",
			"profile_photo": "https://image.tmdb.org/t/p/original/oPIfGm3mf4lbmO5pWwMvfTt5BM1.jpg"
		}
	},
	{
		"model": "movies.actor",
		"pk": 17288,
		"fields": {
			"movie_id": 320288,
			"name": "Michael Fassbender",
			"character": "Erik Lensherr / Magneto",
			"profile_photo": "https://image.tmdb.org/t/p/original/oexNPLumoFpazzzUqzBSDDYiUg1.jpg"
		}
	},
	{
		"model": "movies.actor",
		"pk": 72129,
		"fields": {
			"movie_id": 320288,
			"name": "Jennifer Lawrence",
			"character": "Raven Darkholme / Mystique",
			"profile_photo": "https://image.tmdb.org/t/p/original/naZyy9IqAQDaAbr1kYShLdg6aPR.jpg"
		}
	},
	{
		"model": "movies.actor",
		"pk": 83002,
		"fields": {
			"movie_id": 320288,
			"name": "Jessica Chastain",
			"character": "Vuk",
			"profile_photo": "https://image.tmdb.org/t/p/original/lodMzLKSdrPcBry6TdoDsMN3Vge.jpg"
		}
	},
	{
		"model": "movies.actor",
		"pk": 563838,
		"fields": {
			"movie_id": 71805,
			"name": "Stian Smestad",
			"character": "Haakon Haakonsen",
			"profile_photo": []
		}
	},
	{
		"model": "movies.actor",
		"pk": 5168,
		"fields": {
			"movie_id": 71805,
			"name": "Gabriel Byrne",
			"character": "Lt. John Merrick",
			"profile_photo": "https://image.tmdb.org/t/p/original/yQR6Exu12940oRXoCWmwULyWLP8.jpg"
		}
	},
	{
		"model": "movies.actor",
		"pk": 137748,
		"fields": {
			"movie_id": 71805,
			"name": "Louisa Milwood-Haigh",
			"character": "Mary",
			"profile_photo": "https://image.tmdb.org/t/p/original/dyB9fdYCZLqPhB6PYUosIJBbrBE.jpg"
		}
	},
	{
		"model": "movies.actor",
		"pk": 71186,
		"fields": {
			"movie_id": 71805,
			"name": "Bjørn Sundquist",
			"character": "Mr. Håkonsen",
			"profile_photo": "https://image.tmdb.org/t/p/original/rcyiS1fiGAngHYZoVor5Xiznewp.jpg"
		}
	},
	{
		"model": "movies.actor",
		"pk": 135121,
		"fields": {
			"movie_id": 71805,
			"name": "Joachim Rafaelsen",
			"character": "Ole",
			"profile_photo": "https://image.tmdb.org/t/p/original/s5S2A0ZeDhwlSMAsdZK0izrUNES.jpg"
		}
	},
	{
		"model": "movies.actor",
		"pk": 109,
		"fields": {
			"movie_id": 122,
			"name": "Elijah Wood",
			"character": "Frodo Baggins",
			"profile_photo": "https://image.tmdb.org/t/p/original/ayARmqAe9Aab1zg6FjJG0u9MEBo.jpg"
		}
	},
	{
		"model": "movies.actor",
		"pk": 1327,
		"fields": {
			"movie_id": 122,
			"name": "Ian McKellen",
			"character": "Gandalf the White",
			"profile_photo": "https://image.tmdb.org/t/p/original/coWjgMEYJjk2OrNddlXCBm8EIr3.jpg"
		}
	},
	{
		"model": "movies.actor",
		"pk": 110,
		"fields": {
			"movie_id": 122,
			"name": "Viggo Mortensen",
			"character": "Aragorn",
			"profile_photo": "https://image.tmdb.org/t/p/original/kIyavVDiV6veUbxxxhjITtFLdDY.jpg"
		}
	},
	{
		"model": "movies.actor",
		"pk": 1328,
		"fields": {
			"movie_id": 122,
			"name": "Sean Astin",
			"character": "Samwise \"Sam\" Gamgee",
			"profile_photo": "https://image.tmdb.org/t/p/original/j7ufzsiGkUck6HUAuQciXVnowmO.jpg"
		}
	},
	{
		"model": "movies.actor",
		"pk": 882,
		"fields": {
			"movie_id": 122,
			"name": "Liv Tyler",
			"character": "Arwen Evenstar",
			"profile_photo": "https://image.tmdb.org/t/p/original/lD2YnrKdnRUvFDMSiK2pw13ZMIB.jpg"
		}
	},
	{
		"model": "movies.actor",
		"pk": 4,
		"fields": {
			"movie_id": 181812,
			"name": "Carrie Fisher",
			"character": "General Leia Organa",
			"profile_photo": "https://image.tmdb.org/t/p/original/rfJtncHewKVnHjqpIZvjn24ESeC.jpg"
		}
	},
	{
		"model": "movies.actor",
		"pk": 2,
		"fields": {
			"movie_id": 181812,
			"name": "Mark Hamill",
			"character": "Luke Skywalker",
			"profile_photo": "https://image.tmdb.org/t/p/original/fk8OfdReNltKZqOk2TZgkofCUFq.jpg"
		}
	},
	{
		"model": "movies.actor",
		"pk": 1023139,
		"fields": {
			"movie_id": 181812,
			"name": "Adam Driver",
			"character": "Kylo Ren",
			"profile_photo": "https://image.tmdb.org/t/p/original/rsjwgpV2OukxOJ9HEiEyf4qu1vR.jpg"
		}
	},
	{
		"model": "movies.actor",
		"pk": 1315036,
		"fields": {
			"movie_id": 181812,
			"name": "Daisy Ridley",
			"character": "Rey",
			"profile_photo": "https://image.tmdb.org/t/p/original/oP7khxQ6BUNoGiPFUCI8dikN0ew.jpg"
		}
	},
	{
		"model": "movies.actor",
		"pk": 236695,
		"fields": {
			"movie_id": 181812,
			"name": "John Boyega",
			"character": "Finn",
			"profile_photo": "https://image.tmdb.org/t/p/original/idr2vphzhidyMGOp0ky6RqUMah8.jpg"
		}
	},
	{
		"model": "movies.actor",
		"pk": 227454,
		"fields": {
			"movie_id": 513409,
			"name": "Alicia Vikander",
			"character": "Lucy Fly",
			"profile_photo": "https://image.tmdb.org/t/p/original/oEgh5Clk8l0O5N60I8CsC2bk6QM.jpg"
		}
	},
	{
		"model": "movies.actor",
		"pk": 98522,
		"fields": {
			"movie_id": 513409,
			"name": "Riley Keough",
			"character": "Lily Bridges",
			"profile_photo": "https://image.tmdb.org/t/p/original/eg1PAXJMgmwTO4UeW7p7oBPKMbU.jpg"
		}
	},
	{
		"model": "movies.actor",
		"pk": 1986542,
		"fields": {
			"movie_id": 513409,
			"name": "Naoki Kobayashi",
			"character": "Teiji Matsuda",
			"profile_photo": "https://image.tmdb.org/t/p/original/pzuf4gW1gWIFPXuC4pY5uachRym.jpg"
		}
	},
	{
		"model": "movies.actor",
		"pk": 1466601,
		"fields": {
			"movie_id": 513409,
			"name": "Kiki Sukezane",
			"character": "Natsuko",
			"profile_photo": "https://image.tmdb.org/t/p/original/qVYJhP7pnTUAjyaHvL1Hqxw12Qh.jpg"
		}
	},
	{
		"model": "movies.actor",
		"pk": 213473,
		"fields": {
			"movie_id": 513409,
			"name": "Yoshiko Sakuma",
			"character": "Mrs. Yamamoto",
			"profile_photo": "https://image.tmdb.org/t/p/original/dyQVF3AmX6oZSMPZ1SiikPQqpoZ.jpg"
		}
	}
]